async_dnsbl_client/__init__.py
async_dnsbl_client/dnsbl_zones.py
async_dnsbl_client-0.0.5.data/scripts/adnsbl.py
async_dnsbl_client-0.0.5.dist-info/licenses/LICENSE
async_dnsbl_client-0.0.5.dist-info/METADATA
async_dnsbl_client-0.0.5.dist-info/WHEEL
async_dnsbl_client-0.0.5.dist-info/top_level.txt
async_dnsbl_client-0.0.5.dist-info/RECORD
