Metadata-Version: 2.4
Name: async-dnsbl-client
Version: 0.0.5
Summary: Asynchronous dnsbl client module and CLI utility
Home-page: https://github.com/yaroslaff/async-dnsbl-client
Author: Yaroslav Polyakov
Author-email: yaroslaff@gmail.com
License: MIT
Classifier: Development Status :: 3 - Alpha
Classifier: Intended Audience :: Developers
Classifier: License :: OSI Approved :: MIT License
Classifier: Programming Language :: Python :: 3.6
Requires-Python: >=3
License-File: LICENSE
Requires-Dist: aiodns
Dynamic: author
Dynamic: author-email
Dynamic: classifier
Dynamic: description
Dynamic: description-content-type
Dynamic: home-page
Dynamic: license
Dynamic: license-file
Dynamic: requires-dist
Dynamic: requires-python
Dynamic: summary
